rishabh_ask_ai/.env
rishabh_ask_ai/__init__.py
rishabh_ask_ai/main.py
rishabh_ask_ai-1.0.0.post2.dist-info/WHEEL
rishabh_ask_ai-1.0.0.post2.dist-info/entry_points.txt
rishabh_ask_ai-1.0.0.post2.dist-info/METADATA
rishabh_ask_ai-1.0.0.post2.dist-info/RECORD
