Metadata-Version: 2.3
Name: rishabh-ask-ai
Version: 1.0.0.post2
Summary: This is a python package which can return outputs given by ChatGPT using groq
Author: Rishabh Birthalia
Author-email: Rishabh Birthalia <rishabh14b@gmail.com>
Requires-Dist: groq
Requires-Dist: python-dotenv
Requires-Python: >=3.10
